SCFpy/__init__.py
SCFpy/iterator.py
SCFpy/main.py
SCFpy/parser.py
SCFpy/scf.py
SCFpy-0.2.dist-info/DESCRIPTION.rst
SCFpy-0.2.dist-info/METADATA
SCFpy-0.2.dist-info/RECORD
SCFpy-0.2.dist-info/WHEEL
SCFpy-0.2.dist-info/entry_points.txt
SCFpy-0.2.dist-info/metadata.json
SCFpy-0.2.dist-info/top_level.txt
