Metadata-Version: 2.0
Name: SCFpy
Version: 0.2
Summary: A Simple restricted Hartree-Fock code
Home-page: https://github.com/pudu1991/SCFpy
Author: Pu Du
Author-email: rocketsboy@gmail.com
License: MIT
Keywords: A Simple restricted Hartree-Fock code
Platform: UNKNOWN
Classifier: Development Status :: 3 - Alpha
Classifier: Environment :: Console
Classifier: Intended Audience :: Developers
Classifier: Programming Language :: Python :: 2
Classifier: Programming Language :: Python :: 2.6
Classifier: Programming Language :: Python :: 2.7
Classifier: Programming Language :: Python :: 3
Classifier: Programming Language :: Python :: 3.2
Classifier: Programming Language :: Python :: 3.3
Classifier: Programming Language :: Python :: 3.4
Classifier: Topic :: Scientific/Engineering :: Chemistry
Requires-Dist: numpy
